{
    "JobSpecName": "Job with multiple event occurrences",
    "EventDefinition": [
        {
            "EventId": "1",
            "PreviousEventId": "None",
            "EventName": "A",
            "SequenceStart": "true",
            "NodeName": "default_node_name",
            "ApplicationName": "default_application_name"
        },
        {
            "EventId": "2",
            "PreviousEventId": "1",
            "EventName": "B",
            "SequenceStart": "false",
            "NodeName": "default_node_name",
            "ApplicationName": "default_application_name"
        },
        {
            "EventId": "3",
            "PreviousEventId": "2",
            "EventName": "C",
            "SequenceStart": "false",
            "NodeName": "default_node_name",
            "ApplicationName": "default_application_name"
        },
        {
            "EventId": "4",
            "PreviousEventId": "3",
            "EventName": "B",
            "SequenceStart": "false",
            "NodeName": "default_node_name",
            "ApplicationName": "default_application_name"
        },
        {
            "EventId": "5",
            "PreviousEventId": "4",
            "EventName": "C",
            "SequenceStart": "false",
            "NodeName": "default_node_name",
            "ApplicationName": "default_application_name"
        },
        {
            "EventId": "6",
            "PreviousEventId": "3",
            "EventName": "D",
            "SequenceStart": "false",
            "NodeName": "default_node_name",
            "ApplicationName": "default_application_name"
        }
    ]
}
